schedulark/__init__.py
schedulark/base/__init__.py
schedulark/base/cronable.py
schedulark/base/job.py
schedulark/base/task.py
schedulark/planner.py
schedulark/queue/__init__.py
schedulark/queue/json/__init__.py
schedulark/queue/json/json_queue.py
schedulark/queue/memory/__init__.py
schedulark/queue/memory/memory_queue.py
schedulark/queue/queue.py
schedulark/queue/sql/__init__.py
schedulark/queue/sql/connector.py
schedulark/queue/sql/migrations.py
schedulark/queue/sql/sql_queue.py
schedulark/scheduler.py
schedulark/worker/__init__.py
schedulark/worker/worker.py
schedulark-0.1.8.dist-info/LICENSE
schedulark-0.1.8.dist-info/WHEEL
schedulark-0.1.8.dist-info/METADATA
schedulark-0.1.8.dist-info/RECORD
