Metadata-Version: 2.1
Name: schedulark
Version: 0.1.8
Summary: Job Scheduling Library
License: MIT
Author: Knowark
Requires-Python: >=3.8,<4.0
Classifier: License :: OSI Approved :: MIT License
Classifier: Programming Language :: Python :: 3
Classifier: Programming Language :: Python :: 3.8
Classifier: Programming Language :: Python :: 3.9
